pipeloom/__init__.py
pipeloom/cli.py
pipeloom/db.py
pipeloom/demo.py
pipeloom/engine.py
pipeloom/messages.py
pipeloom/progress.py
pipeloom/rlog.py
pipeloom/writer.py
pipeloom/examples/__init__.py
pipeloom/examples/csv_loader.py
pipeloom/examples/etl_http_json_sqlite.py
pipeloom/examples/file_writer.py
pipeloom/examples/http_downloader.py
pipeloom-0.0.7.dist-info/licenses/LICENSE
pipeloom-0.0.7.dist-info/METADATA
pipeloom-0.0.7.dist-info/WHEEL
pipeloom-0.0.7.dist-info/entry_points.txt
pipeloom-0.0.7.dist-info/top_level.txt
pipeloom-0.0.7.dist-info/RECORD
