Metadata-Version: 2.4
Name: pipeloom
Version: 0.0.7
Summary: Lightweight Python framework for orchestrating concurrent tasks with a single-writer persistence model and live progress tracking.
Author-email: Caleb Grant <grantcaleb22@gmail.com>
License-Expression: GPL-3.0-or-later
Project-URL: Homepage, https://pipeloom.readthedocs.io/en/latest/
Project-URL: Repository, https://github.com/geocoug/pipeloom
Project-URL: Issues, https://github.com/geocoug/pipeloom/issues
Requires-Python: <3.14,>=3.12
License-File: LICENSE
Requires-Dist: rich>=14.1.0
Requires-Dist: typer>=0.16.0
Provides-Extra: dev
Requires-Dist: build>=1.3.0; extra == "dev"
Requires-Dist: bump-my-version>=1.2.1; extra == "dev"
Requires-Dist: pre-commit>=4.3.0; extra == "dev"
Requires-Dist: pytest-cov>=6.2.1; extra == "dev"
Requires-Dist: ruff>=0.12.8; extra == "dev"
Requires-Dist: tox-uv>=1.27.0; extra == "dev"
Requires-Dist: twine>=6.1.0; extra == "dev"
Provides-Extra: docs
Requires-Dist: markdown-include>=0.8.1; extra == "docs"
Requires-Dist: mkdocs>=1.6.1; extra == "docs"
Requires-Dist: mkdocs-material>=9.6.16; extra == "docs"
Requires-Dist: mkdocs-mermaid2-plugin>=1.2.1; extra == "docs"
Requires-Dist: mkdocs-typer>=0.0.3; extra == "docs"
Requires-Dist: mkdocstrings[python]>=0.30.0; extra == "docs"
Requires-Dist: pymdown-extensions>=10.16.1; extra == "docs"
Provides-Extra: examples
Requires-Dist: polars>=1.32.2; extra == "examples"
Requires-Dist: requests>=2.32.4; extra == "examples"
Dynamic: license-file
